intelligence/__init__.py
intelligence-0.1.dist-info/METADATA
intelligence-0.1.dist-info/WHEEL
intelligence-0.1.dist-info/top_level.txt
intelligence-0.1.dist-info/RECORD
