Metadata-Version: 2.1
Name: intelligence
Version: 0.1
Summary: Python library for navigating the internet
Home-page: https://github.com/idin/intelligence
Author: Idin
Author-email: py@idin.ca
License: MIT
Platform: UNKNOWN
Classifier: Development Status :: 3 - Alpha
Classifier: Intended Audience :: Developers
Classifier: Programming Language :: Python :: 3 :: Only
Classifier: Programming Language :: Python :: 3.6
Classifier: Programming Language :: Python :: 3.7
Classifier: Topic :: Software Development :: Libraries :: Python Modules
Requires-Python: ~=3.6
